pygame_click_manager/__init__.py
pygame_click_manager/click_manager.py
pygame_click_manager-1.0.dist-info/METADATA
pygame_click_manager-1.0.dist-info/WHEEL
pygame_click_manager-1.0.dist-info/top_level.txt
pygame_click_manager-1.0.dist-info/RECORD
