Metadata-Version: 2.1
Name: pygame-click-manager
Version: 1.0
Summary: A package for managing clicks in pygame.
Home-page: https://github.com/FrickTzy/Pygame-Click-Manager
Author: FrickTzy (Kurt Arnoco)
License: UNKNOWN
Keywords: python,pygame,python game,python game development,pygame button
Platform: UNKNOWN
